josiauhtools_josiauh/__init__.py
josiauhtools_josiauh/__main__.py
josiauhtools_josiauh/exvenvded.py
josiauhtools_josiauh/grazio.py
josiauhtools_josiauh/synx.py
josiauhtools-0.0.3.dist-info/LICENSE
josiauhtools-0.0.3.dist-info/METADATA
josiauhtools-0.0.3.dist-info/WHEEL
josiauhtools-0.0.3.dist-info/top_level.txt
josiauhtools-0.0.3.dist-info/RECORD
