Metadata-Version: 2.1
Name: josiauhtools
Version: 0.0.3
Summary: Some tools for python.
Author: Josiah
Project-URL: Repository, https://github.com/josiauh/josiauhtools
Keywords: tools
Classifier: Programming Language :: Python :: 3
Classifier: License :: OSI Approved :: MIT License
Classifier: Operating System :: OS Independent
Requires-Python: >=3.8
License-File: LICENSE
Requires-Dist: yachalk
